<?xml version="1.0" encoding="utf-8"?>
<!DOCTYPE hibernate-mapping PUBLIC "-//Hibernate/Hibernate Mapping DTD 3.0//EN"
"http://hibernate.sourceforge.net/hibernate-mapping-3.0.dtd">
<!-- 
    Mapping file autogenerated by MyEclipse Persistence Tools
-->
<hibernate-mapping package="com.jinyb.crawler.entity">
    <class name="Column" table="article_column" catalog="themecrawler">
        <id name="id" type="integer">
            <column name="c_id" />
            <generator class="increment"></generator>
        </id>
        <property name="column" type="string">
            <column name="c_column" length="45" not-null="true" />
        </property>
        <set name="article" cascade="all" inverse="false">
             <key column="n_c_id">  </key><!-- 设置一对多关联，cascade进行所有级联操作
             inverse为真，表示将控制权限交给news表，及对news.cid关联字段的操作权限 -->
             <one-to-many class="Article"/>
        </set>
    </class>
</hibernate-mapping>
